aggregator/__init__.py
aggregator/aggregate.py
aggregator/plot.py
pdf_aggregator-0.0.1.dist-info/LICENSE
pdf_aggregator-0.0.1.dist-info/METADATA
pdf_aggregator-0.0.1.dist-info/WHEEL
pdf_aggregator-0.0.1.dist-info/entry_points.txt
pdf_aggregator-0.0.1.dist-info/top_level.txt
pdf_aggregator-0.0.1.dist-info/RECORD
