Metadata-Version: 2.1
Name: pdf-aggregator
Version: 0.0.1
Summary: Aggregate account PDF statements into JSON and visualize aggregated financial data as timeline
Home-page: https://github.com/finetjul/pdf-aggregator
Author: Julien Finet
Author-email: julien.finet@kitware.com
License: UNKNOWN
Keywords: pdf aggregate extract banking financial statement
Platform: UNKNOWN
Classifier: Programming Language :: Python :: 3
Classifier: License :: OSI Approved :: ISC License (ISCL)
Classifier: Operating System :: OS Independent
Requires-Python: >=3.6
